schematics_to_swagger/__init__.py
schematics_to_swagger-1.4.7.dist-info/LICENSE
schematics_to_swagger-1.4.7.dist-info/METADATA
schematics_to_swagger-1.4.7.dist-info/WHEEL
schematics_to_swagger-1.4.7.dist-info/top_level.txt
schematics_to_swagger-1.4.7.dist-info/RECORD
