Metadata-Version: 2.1
Name: schematics-to-swagger
Version: 1.4.7
Summary: Helper library to build Swagger Schema objects from Schematics models
Home-page: https://github.com/Alexei-Kornienko/schematics_to_swagger
Author: Alexei Kornienko
Author-email: alexei.kornienko@gmail.com
License: MIT
Platform: UNKNOWN
Classifier: Programming Language :: Python :: 3.4
Classifier: Programming Language :: Python :: 3.5
Classifier: Programming Language :: Python :: 3.6
Classifier: Programming Language :: Python :: 3.7
Requires-Dist: schematics
